idrc/__init__.py
idrc/colors.py
idrc/core.py
idrc/helpers.py
idrc/request_handler.py
idrc-1.5.0.dist-info/LICENSE
idrc-1.5.0.dist-info/METADATA
idrc-1.5.0.dist-info/WHEEL
idrc-1.5.0.dist-info/top_level.txt
idrc-1.5.0.dist-info/RECORD
