Metadata-Version: 2.1
Name: idrc
Version: 1.5.0
Summary: Auto APIs for lazy people.
Home-page: https://github.com/zanderlewis/idrc
Author: Zander Lewis
Author-email: zander@zanderlewis.dev
Classifier: Programming Language :: Python :: 3
Classifier: License :: OSI Approved :: MIT License
Classifier: Operating System :: OS Independent
Requires-Python: >=3.6
License-File: LICENSE
